ladybug_display_schema/__init__.py
ladybug_display_schema/base.py
ladybug_display_schema/display2d.py
ladybug_display_schema/display3d.py
ladybug_display_schema/geometry2d.py
ladybug_display_schema/geometry3d.py
ladybug_display_schema/visualization.py
ladybug_display_schema-0.7.8.dist-info/LICENSE
ladybug_display_schema-0.7.8.dist-info/METADATA
ladybug_display_schema-0.7.8.dist-info/WHEEL
ladybug_display_schema-0.7.8.dist-info/top_level.txt
ladybug_display_schema-0.7.8.dist-info/RECORD
