Metadata-Version: 2.1
Name: ladybug-display-schema
Version: 0.7.8
Summary: Ladybug-display Data-Model Objects
Home-page: https://github.com/ladybug-tools/ladybug-display-schema
Author: Ladybug Tools
Author-email: info@ladybug.tools
License: UNKNOWN
Platform: UNKNOWN
Classifier: Programming Language :: Python :: 3.7
Classifier: Programming Language :: Python :: 3.10
Classifier: Programming Language :: Python :: Implementation :: CPython
Classifier: Operating System :: OS Independent
License-File: LICENSE
Requires-Dist: pydantic-openapi-helper (>=0.2.10)
